fusionsent/__init__.py
fusionsent/merging_methods.py
fusionsent/modeling.py
fusionsent/trainer.py
fusionsent/training_args.py
fusionsent-0.0.9.dist-info/LICENSE.txt
fusionsent-0.0.9.dist-info/METADATA
fusionsent-0.0.9.dist-info/WHEEL
fusionsent-0.0.9.dist-info/top_level.txt
fusionsent-0.0.9.dist-info/RECORD
