Metadata-Version: 2.1
Name: fusionsent
Version: 0.0.9
Summary: FusionSent: A Fusion-Based Multi-Task Sentence Embedding Model
Home-page: https://github.com/sebischair/FusionSent
Author: Tim Schopf, Alexander Blatzheim
Author-email: tim.schopf@tum.de, alexander.blatzheim@tum.de
License: Apache-2.0
Classifier: Programming Language :: Python :: 3.10
Classifier: License :: OSI Approved :: Apache Software License
Classifier: Operating System :: OS Independent
Requires-Python: >=3.10
License-File: LICENSE.txt
Requires-Dist: accelerate==0.32.1
Requires-Dist: aiohappyeyeballs==2.4.3
Requires-Dist: aiohttp==3.9.5
Requires-Dist: aiosignal==1.3.1
Requires-Dist: async-timeout==4.0.3
Requires-Dist: attrs==23.2.0
Requires-Dist: certifi==2024.8.30
Requires-Dist: charset-normalizer==3.3.2
Requires-Dist: datasets==2.20.0
Requires-Dist: dill==0.3.5.1
Requires-Dist: evaluate==0.4.2
Requires-Dist: filelock==3.15.4
Requires-Dist: frozenlist==1.4.1
Requires-Dist: fsspec==2023.10.0
Requires-Dist: huggingface-hub==0.21.2
Requires-Dist: idna==3.10
Requires-Dist: Jinja2==3.1.4
Requires-Dist: joblib==1.4.2
Requires-Dist: MarkupSafe==2.1.5
Requires-Dist: mpmath==1.3.0
Requires-Dist: multidict==6.0.5
Requires-Dist: multiprocess==0.70.13
Requires-Dist: networkx==3.3
Requires-Dist: numpy==1.23.5
Requires-Dist: packaging==24.1
Requires-Dist: pandas==2.2.2
Requires-Dist: pillow==10.4.0
Requires-Dist: psutil==6.0.0
Requires-Dist: pyarrow==15.0.0
Requires-Dist: python-dateutil==2.9.0.post0
Requires-Dist: pytz==2024.2
Requires-Dist: PyYAML==6.0.1
Requires-Dist: regex==2024.5.15
Requires-Dist: requests==2.32.3
Requires-Dist: safetensors==0.4.3
Requires-Dist: scikit-learn==1.5.1
Requires-Dist: scipy==1.10.1
Requires-Dist: sentence-transformers==3.0.1
Requires-Dist: setfit==1.0.3
Requires-Dist: six==1.16.0
Requires-Dist: sympy==1.13.3
Requires-Dist: threadpoolctl==3.5.0
Requires-Dist: tokenizers==0.19.1
Requires-Dist: torch==2.3.1
Requires-Dist: tqdm==4.66.4
Requires-Dist: transformers==4.40.0
Requires-Dist: typing_extensions==4.12.2
Requires-Dist: tzdata==2024.1
Requires-Dist: urllib3==2.2.2
Requires-Dist: xxhash==3.4.1
Requires-Dist: yarl==1.9.4
